bildkedde/__init__.py
bildkedde/simple_sensor_model.py
bildkedde/version_info.py
bildkedde/core/__init__.py
bildkedde/core/link.py
bildkedde/core/render.py
bildkedde/core/transform.py
bildkedde/core/utils.py
bildkedde-0.0.1.dev0.dist-info/LICENSE
bildkedde-0.0.1.dev0.dist-info/METADATA
bildkedde-0.0.1.dev0.dist-info/WHEEL
bildkedde-0.0.1.dev0.dist-info/top_level.txt
bildkedde-0.0.1.dev0.dist-info/RECORD
