Metadata-Version: 2.1
Name: bildkedde
Version: 0.0.1.dev0
Summary: Lightweight sensor modeling package
Home-page: https://ryanhartzell.github.io/Bildkedde
Author: Ryan Hartzell
Author-email: bildkedde@gmail.com
Maintainer: Ryan Hartzell
Maintainer-email: bildkedde@gmail.com
License: MIT
Download-URL: https://github.com/RyanHartzell/Bildkedde
Keywords: imaging-science sensor-model image-chain optics radiometry
Platform: Windows
Platform: Linux
Platform: Mac OS-X
Platform: Unix
Classifier: Development Status :: 1 - Planning
Classifier: Intended Audience :: Science/Research
Classifier: Intended Audience :: Education
Classifier: Topic :: Scientific/Engineering
Classifier: Topic :: Scientific/Engineering :: Image Processing
Classifier: Topic :: Scientific/Engineering :: Physics
Classifier: Topic :: Scientific/Engineering :: Information Analysis
Classifier: License :: OSI Approved :: MIT License
Classifier: Programming Language :: Python
Classifier: Programming Language :: Python :: 3
Classifier: Programming Language :: Python :: 3.7
Classifier: Programming Language :: Python :: 3.8
Classifier: Programming Language :: Python :: Implementation :: CPython
Classifier: Operating System :: MacOS :: MacOS X
Classifier: Operating System :: Microsoft :: Windows
Classifier: Operating System :: POSIX
Classifier: Natural Language :: English
Requires-Python: >=3.7.*
Requires-Dist: certifi (==2020.6.20)
Requires-Dist: cycler (==0.10.0)
Requires-Dist: imageio (==2.9.0)
Requires-Dist: kiwisolver (==1.2.0)
Requires-Dist: matplotlib (==3.3.2)
Requires-Dist: numpy (==1.19.2)
Requires-Dist: Pillow (==8.0.0)
Requires-Dist: pyparsing (==2.4.7)
Requires-Dist: python-dateutil (==2.8.1)
Requires-Dist: scipy (==1.6.3)
Requires-Dist: six (==1.15.0)
Provides-Extra: dev
Requires-Dist: bleach (==3.3.0) ; extra == 'dev'
Requires-Dist: build (==0.3.1.post1) ; extra == 'dev'
Requires-Dist: certifi (==2020.6.20) ; extra == 'dev'
Requires-Dist: cffi (==1.14.5) ; extra == 'dev'
Requires-Dist: chardet (==4.0.0) ; extra == 'dev'
Requires-Dist: colorama (==0.4.4) ; extra == 'dev'
Requires-Dist: cryptography (==3.4.7) ; extra == 'dev'
Requires-Dist: cycler (==0.10.0) ; extra == 'dev'
Requires-Dist: docutils (==0.17.1) ; extra == 'dev'
Requires-Dist: idna (==2.10) ; extra == 'dev'
Requires-Dist: imageio (==2.9.0) ; extra == 'dev'
Requires-Dist: importlib-metadata (==4.0.1) ; extra == 'dev'
Requires-Dist: jeepney (==0.6.0) ; extra == 'dev'
Requires-Dist: keyring (==23.0.1) ; extra == 'dev'
Requires-Dist: kiwisolver (==1.2.0) ; extra == 'dev'
Requires-Dist: matplotlib (==3.3.2) ; extra == 'dev'
Requires-Dist: numpy (==1.19.2) ; extra == 'dev'
Requires-Dist: packaging (==20.9) ; extra == 'dev'
Requires-Dist: pep517 (==0.10.0) ; extra == 'dev'
Requires-Dist: Pillow (==8.0.0) ; extra == 'dev'
Requires-Dist: pkginfo (==1.7.0) ; extra == 'dev'
Requires-Dist: pycparser (==2.20) ; extra == 'dev'
Requires-Dist: Pygments (==2.8.1) ; extra == 'dev'
Requires-Dist: pyparsing (==2.4.7) ; extra == 'dev'
Requires-Dist: python-dateutil (==2.8.1) ; extra == 'dev'
Requires-Dist: readme-renderer (==29.0) ; extra == 'dev'
Requires-Dist: requests (==2.25.1) ; extra == 'dev'
Requires-Dist: requests-toolbelt (==0.9.1) ; extra == 'dev'
Requires-Dist: rfc3986 (==1.4.0) ; extra == 'dev'
Requires-Dist: scipy (==1.6.3) ; extra == 'dev'
Requires-Dist: SecretStorage (==3.3.1) ; extra == 'dev'
Requires-Dist: six (==1.15.0) ; extra == 'dev'
Requires-Dist: toml (==0.10.2) ; extra == 'dev'
Requires-Dist: tqdm (==4.60.0) ; extra == 'dev'
Requires-Dist: twine (==3.4.1) ; extra == 'dev'
Requires-Dist: urllib3 (==1.26.4) ; extra == 'dev'
Requires-Dist: webencodings (==0.5.1) ; extra == 'dev'
Requires-Dist: zipp (==3.4.1) ; extra == 'dev'
